LICENSE.md
MANIFEST.in
Makefile
README.md
pyproject.toml
requirements.txt
setup.py
limnoria.egg-info/PKG-INFO
limnoria.egg-info/SOURCES.txt
limnoria.egg-info/dependency_links.txt
limnoria.egg-info/entry_points.txt
limnoria.egg-info/top_level.txt
locales/__init__.py
locales/de.po
locales/fi.po
locales/fr.po
locales/fr.py
locales/it.po
locales/messages.pot
locales/ru.po
man/limnoria-adduser.1
man/limnoria-botchk.1
man/limnoria-plugin-create.1
man/limnoria-plugin-doc.1
man/limnoria-reset-password.1
man/limnoria-test.1
man/limnoria-wizard.1
man/limnoria.1
man/supybot-adduser.1
man/supybot-botchk.1
man/supybot-plugin-create.1
man/supybot-plugin-doc.1
man/supybot-reset-password.1
man/supybot-test.1
man/supybot-wizard.1
man/supybot.1
plugins/__init__.py
plugins/Admin/__init__.py
plugins/Admin/config.py
plugins/Admin/plugin.py
plugins/Admin/test.py
plugins/Admin/locales/de.po
plugins/Admin/locales/fi.po
plugins/Admin/locales/fr.po
plugins/Admin/locales/it.po
plugins/Aka/__init__.py
plugins/Aka/config.py
plugins/Aka/plugin.py
plugins/Aka/test.py
plugins/Aka/locales/fi.po
plugins/Aka/locales/ru.po
plugins/Alias/__init__.py
plugins/Alias/config.py
plugins/Alias/plugin.py
plugins/Alias/test.py
plugins/Alias/locales/de.po
plugins/Alias/locales/fi.po
plugins/Alias/locales/fr.po
plugins/Alias/locales/hu.po
plugins/Alias/locales/it.po
plugins/Anonymous/__init__.py
plugins/Anonymous/config.py
plugins/Anonymous/plugin.py
plugins/Anonymous/test.py
plugins/Anonymous/locales/de.po
plugins/Anonymous/locales/fi.po
plugins/Anonymous/locales/fr.po
plugins/Anonymous/locales/hu.po
plugins/Anonymous/locales/it.po
plugins/Anonymous/locales/ru.po
plugins/AutoMode/__init__.py
plugins/AutoMode/config.py
plugins/AutoMode/plugin.py
plugins/AutoMode/test.py
plugins/AutoMode/locales/de.po
plugins/AutoMode/locales/fi.po
plugins/AutoMode/locales/fr.po
plugins/AutoMode/locales/it.po
plugins/Autocomplete/__init__.py
plugins/Autocomplete/config.py
plugins/Autocomplete/plugin.py
plugins/Autocomplete/test.py
plugins/BadWords/__init__.py
plugins/BadWords/config.py
plugins/BadWords/plugin.py
plugins/BadWords/test.py
plugins/BadWords/locales/fi.po
