Metadata-Version: 2.4
Name: limnoria
Version: 2026.1.16
Summary: A multipurpose Python IRC bot, designed for flexibility and robustness , while being easy to install, set up, and maintain.
Home-page: https://limnoria.net/
Download-URL: https://pypi.python.org/pypi/limnoria
Author: Valentin Lorentz
Author-email: progval+limnoria@progval.net
License: BSD-3-Clause
Platform: linux
Platform: linux2
Platform: win32
Platform: cygwin
Platform: darwin
Classifier: Development Status :: 5 - Production/Stable
Classifier: Environment :: Console
Classifier: Environment :: No Input/Output (Daemon)
Classifier: Intended Audience :: End Users/Desktop
Classifier: Intended Audience :: Developers
Classifier: Natural Language :: English
Classifier: Natural Language :: Finnish
Classifier: Natural Language :: French
Classifier: Natural Language :: Hungarian
Classifier: Natural Language :: Italian
Classifier: Operating System :: OS Independent
Classifier: Operating System :: POSIX
Classifier: Operating System :: Microsoft :: Windows
Classifier: Programming Language :: Python :: 3.9
Classifier: Programming Language :: Python :: 3.10
Classifier: Programming Language :: Python :: 3.11
Classifier: Programming Language :: Python :: 3.12
Classifier: Programming Language :: Python :: 3.13
Classifier: Topic :: Communications :: Chat :: Internet Relay Chat
Classifier: Topic :: Software Development :: Libraries :: Python Modules
Provides: supybot
License-File: LICENSE.md
Dynamic: author
Dynamic: author-email
Dynamic: classifier
Dynamic: description
Dynamic: download-url
Dynamic: home-page
Dynamic: license
Dynamic: license-file
Dynamic: platform
Dynamic: provides
Dynamic: summary
